dpm/Colours.py
dpm/Menu.py
dpm/__init__.py
dpm/browse_library.py
dpm/client.py
dpm/cs.py
dpm/currently_playing.py
dpm/info_panel.py
dpm/main.py
dpm/playlist.py
dpm/playlist_opt.py
dpm/search.py
dpm/shuffle.py
dpmt-0.0.1.dist-info/METADATA
dpmt-0.0.1.dist-info/WHEEL
dpmt-0.0.1.dist-info/top_level.txt
dpmt-0.0.1.dist-info/RECORD
