Metadata-Version: 2.1
Name: dpmt
Version: 0.0.1
Summary: TUI frontend for MPD
Home-page: https://github.com/shayanaqvi/dpm
Author: Shayan Naqvi
Author-email: shayan.naqvi@icloud.com
Project-URL: Bug Tracker, https://github.com/shayanaqvi/dpm/issues
Project-URL: repository, https://github.com/shayanaqvi/dpm
Classifier: Programming Language :: Python :: 3
Classifier: License :: OSI Approved :: MIT License
Classifier: Operating System :: OS Independent
Requires-Python: >=3.11
